{"bits": 8, "params": [{"name": "conv1.weight", "shape": [80, 40, 3], "q": true, "off": 0, "count": 9600, "scale_off": 0, "nscale": 80}, {"name": "bn1.weight", "shape": [80], "q": false, "f32_off": 80, "count": 80}, {"name": "bn1.bias", "shape": [80], "q": false, "f32_off": 160, "count": 80}, {"name": "bn1.running_mean", "shape": [80], "q": false, "f32_off": 240, "count": 80}, {"name": "bn1.running_var", "shape": [80], "q": false, "f32_off": 320, "count": 80}, {"name": "bn1.num_batches_tracked", "shape": [], "q": false, "f32_off": 400, "count": 1}, {"name": "layer1.0.conv1.weight", "shape": [80, 80, 3], "q": true, "off": 9600, "count": 19200, "scale_off": 401, "nscale": 80}, {"name": "layer1.0.bn1.weight", "shape": [80], "q": false, "f32_off": 481, "count": 80}, {"name": "layer1.0.bn1.bias", "shape": [80], "q": false, "f32_off": 561, "count": 80}, {"name": "layer1.0.bn1.running_mean", "shape": [80], "q": false, "f32_off": 641, "count": 80}, {"name": "layer1.0.bn1.running_var", "shape": [80], "q": false, "f32_off": 721, "count": 80}, {"name": "layer1.0.bn1.num_batches_tracked", "shape": [], "q": false, "f32_off": 801, "count": 1}, {"name": "layer1.0.conv2.weight", "shape": [80, 80, 3], "q": true, "off": 28800, "count": 19200, "scale_off": 802, "nscale": 80}, {"name": "layer1.0.bn2.weight", "shape": [80], "q": false, "f32_off": 882, "count": 80}, {"name": "layer1.0.bn2.bias", "shape": [80], "q": false, "f32_off": 962, "count": 80}, {"name": "layer1.0.bn2.running_mean", "shape": [80], "q": false, "f32_off": 1042, "count": 80}, {"name": "layer1.0.bn2.running_var", "shape": [80], "q": false, "f32_off": 1122, "count": 80}, {"name": "layer1.0.bn2.num_batches_tracked", "shape": [], "q": false, "f32_off": 1202, "count": 1}, {"name": "layer1.0.shortcut.0.weight", "shape": [80, 80, 1], "q": true, "off": 48000, "count": 6400, "scale_off": 1203, "nscale": 80}, {"name": "layer1.0.shortcut.1.weight", "shape": [80], "q": false, "f32_off": 1283, "count": 80}, {"name": "layer1.0.shortcut.1.bias", "shape": [80], "q": false, "f32_off": 1363, "count": 80}, {"name": "layer1.0.shortcut.1.running_mean", "shape": [80], "q": false, "f32_off": 1443, "count": 80}, {"name": "layer1.0.shortcut.1.running_var", "shape": [80], "q": false, "f32_off": 1523, "count": 80}, {"name": "layer1.0.shortcut.1.num_batches_tracked", "shape": [], "q": false, "f32_off": 1603, "count": 1}, {"name": "layer1.1.conv1.weight", "shape": [80, 80, 3], "q": true, "off": 54400, "count": 19200, "scale_off": 1604, "nscale": 80}, {"name": "layer1.1.bn1.weight", "shape": [80], "q": false, "f32_off": 1684, "count": 80}, {"name": "layer1.1.bn1.bias", "shape": [80], "q": false, "f32_off": 1764, "count": 80}, {"name": "layer1.1.bn1.running_mean", "shape": [80], "q": false, "f32_off": 1844, "count": 80}, {"name": "layer1.1.bn1.running_var", "shape": [80], "q": false, "f32_off": 1924, "count": 80}, {"name": "layer1.1.bn1.num_batches_tracked", "shape": [], "q": false, "f32_off": 2004, "count": 1}, {"name": "layer1.1.conv2.weight", "shape": [80, 80, 3], "q": true, "off": 73600, "count": 19200, "scale_off": 2005, "nscale": 80}, {"name": "layer1.1.bn2.weight", "shape": [80], "q": false, "f32_off": 2085, "count": 80}, {"name": "layer1.1.bn2.bias", "shape": [80], "q": false, "f32_off": 2165, "count": 80}, {"name": "layer1.1.bn2.running_mean", "shape": [80], "q": false, "f32_off": 2245, "count": 80}, {"name": "layer1.1.bn2.running_var", "shape": [80], "q": false, "f32_off": 2325, "count": 80}, {"name": "layer1.1.bn2.num_batches_tracked", "shape": [], "q": false, "f32_off": 2405, "count": 1}, {"name": "layer2.0.conv1.weight", "shape": [160, 80, 3], "q": true, "off": 92800, "count": 38400, "scale_off": 2406, "nscale": 160}, {"name": "layer2.0.bn1.weight", "shape": [160], "q": false, "f32_off": 2566, "count": 160}, {"name": "layer2.0.bn1.bias", "shape": [160], "q": false, "f32_off": 2726, "count": 160}, {"name": "layer2.0.bn1.running_mean", "shape": [160], "q": false, "f32_off": 2886, "count": 160}, {"name": "layer2.0.bn1.running_var", "shape": [160], "q": false, "f32_off": 3046, "count": 160}, {"name": "layer2.0.bn1.num_batches_tracked", "shape": [], "q": false, "f32_off": 3206, "count": 1}, {"name": "layer2.0.conv2.weight", "shape": [160, 160, 3], "q": true, "off": 131200, "count": 76800, "scale_off": 3207, "nscale": 160}, {"name": "layer2.0.bn2.weight", "shape": [160], "q": false, "f32_off": 3367, "count": 160}, {"name": "layer2.0.bn2.bias", "shape": [160], "q": false, "f32_off": 3527, "count": 160}, {"name": "layer2.0.bn2.running_mean", "shape": [160], "q": false, "f32_off": 3687, "count": 160}, {"name": "layer2.0.bn2.running_var", "shape": [160], "q": false, "f32_off": 3847, "count": 160}, {"name": "layer2.0.bn2.num_batches_tracked", "shape": [], "q": false, "f32_off": 4007, "count": 1}, {"name": "layer2.0.shortcut.0.weight", "shape": [160, 80, 1], "q": true, "off": 208000, "count": 12800, "scale_off": 4008, "nscale": 160}, {"name": "layer2.0.shortcut.1.weight", "shape": [160], "q": false, "f32_off": 4168, "count": 160}, {"name": "layer2.0.shortcut.1.bias", "shape": [160], "q": false, "f32_off": 4328, "count": 160}, {"name": "layer2.0.shortcut.1.running_mean", "shape": [160], "q": false, "f32_off": 4488, "count": 160}, {"name": "layer2.0.shortcut.1.running_var", "shape": [160], "q": false, "f32_off": 4648, "count": 160}, {"name": "layer2.0.shortcut.1.num_batches_tracked", "shape": [], "q": false, "f32_off": 4808, "count": 1}, {"name": "layer2.1.conv1.weight", "shape": [160, 160, 3], "q": true, "off": 220800, "count": 76800, "scale_off": 4809, "nscale": 160}, {"name": "layer2.1.bn1.weight", "shape": [160], "q": false, "f32_off": 4969, "count": 160}, {"name": "layer2.1.bn1.bias", "shape": [160], "q": false, "f32_off": 5129, "count": 160}, {"name": "layer2.1.bn1.running_mean", "shape": [160], "q": false, "f32_off": 5289, "count": 160}, {"name": "layer2.1.bn1.running_var", "shape": [160], "q": false, "f32_off": 5449, "count": 160}, {"name": "layer2.1.bn1.num_batches_tracked", "shape": [], "q": false, "f32_off": 5609, "count": 1}, {"name": "layer2.1.conv2.weight", "shape": [160, 160, 3], "q": true, "off": 297600, "count": 76800, "scale_off": 5610, "nscale": 160}, {"name": "layer2.1.bn2.weight", "shape": [160], "q": false, "f32_off": 5770, "count": 160}, {"name": "layer2.1.bn2.bias", "shape": [160], "q": false, "f32_off": 5930, "count": 160}, {"name": "layer2.1.bn2.running_mean", "shape": [160], "q": false, "f32_off": 6090, "count": 160}, {"name": "layer2.1.bn2.running_var", "shape": [160], "q": false, "f32_off": 6250, "count": 160}, {"name": "layer2.1.bn2.num_batches_tracked", "shape": [], "q": false, "f32_off": 6410, "count": 1}, {"name": "layer3.0.conv1.weight", "shape": [320, 160, 3], "q": true, "off": 374400, "count": 153600, "scale_off": 6411, "nscale": 320}, {"name": "layer3.0.bn1.weight", "shape": [320], "q": false, "f32_off": 6731, "count": 320}, {"name": "layer3.0.bn1.bias", "shape": [320], "q": false, "f32_off": 7051, "count": 320}, {"name": "layer3.0.bn1.running_mean", "shape": [320], "q": false, "f32_off": 7371, "count": 320}, {"name": "layer3.0.bn1.running_var", "shape": [320], "q": false, "f32_off": 7691, "count": 320}, {"name": "layer3.0.bn1.num_batches_tracked", "shape": [], "q": false, "f32_off": 8011, "count": 1}, {"name": "layer3.0.conv2.weight", "shape": [320, 320, 3], "q": true, "off": 528000, "count": 307200, "scale_off": 8012, "nscale": 320}, {"name": "layer3.0.bn2.weight", "shape": [320], "q": false, "f32_off": 8332, "count": 320}, {"name": "layer3.0.bn2.bias", "shape": [320], "q": false, "f32_off": 8652, "count": 320}, {"name": "layer3.0.bn2.running_mean", "shape": [320], "q": false, "f32_off": 8972, "count": 320}, {"name": "layer3.0.bn2.running_var", "shape": [320], "q": false, "f32_off": 9292, "count": 320}, {"name": "layer3.0.bn2.num_batches_tracked", "shape": [], "q": false, "f32_off": 9612, "count": 1}, {"name": "layer3.0.shortcut.0.weight", "shape": [320, 160, 1], "q": true, "off": 835200, "count": 51200, "scale_off": 9613, "nscale": 320}, {"name": "layer3.0.shortcut.1.weight", "shape": [320], "q": false, "f32_off": 9933, "count": 320}, {"name": "layer3.0.shortcut.1.bias", "shape": [320], "q": false, "f32_off": 10253, "count": 320}, {"name": "layer3.0.shortcut.1.running_mean", "shape": [320], "q": false, "f32_off": 10573, "count": 320}, {"name": "layer3.0.shortcut.1.running_var", "shape": [320], "q": false, "f32_off": 10893, "count": 320}, {"name": "layer3.0.shortcut.1.num_batches_tracked", "shape": [], "q": false, "f32_off": 11213, "count": 1}, {"name": "layer3.1.conv1.weight", "shape": [320, 320, 3], "q": true, "off": 886400, "count": 307200, "scale_off": 11214, "nscale": 320}, {"name": "layer3.1.bn1.weight", "shape": [320], "q": false, "f32_off": 11534, "count": 320}, {"name": "layer3.1.bn1.bias", "shape": [320], "q": false, "f32_off": 11854, "count": 320}, {"name": "layer3.1.bn1.running_mean", "shape": [320], "q": false, "f32_off": 12174, "count": 320}, {"name": "layer3.1.bn1.running_var", "shape": [320], "q": false, "f32_off": 12494, "count": 320}, {"name": "layer3.1.bn1.num_batches_tracked", "shape": [], "q": false, "f32_off": 12814, "count": 1}, {"name": "layer3.1.conv2.weight", "shape": [320, 320, 3], "q": true, "off": 1193600, "count": 307200, "scale_off": 12815, "nscale": 320}, {"name": "layer3.1.bn2.weight", "shape": [320], "q": false, "f32_off": 13135, "count": 320}, {"name": "layer3.1.bn2.bias", "shape": [320], "q": false, "f32_off": 13455, "count": 320}, {"name": "layer3.1.bn2.running_mean", "shape": [320], "q": false, "f32_off": 13775, "count": 320}, {"name": "layer3.1.bn2.running_var", "shape": [320], "q": false, "f32_off": 14095, "count": 320}, {"name": "layer3.1.bn2.num_batches_tracked", "shape": [], "q": false, "f32_off": 14415, "count": 1}, {"name": "linear1.weight", "shape": [1024, 1340], "q": true, "off": 1500800, "count": 1372160, "scale_off": 14416, "nscale": 1024}, {"name": "linear1.bias", "shape": [1024], "q": false, "f32_off": 15440, "count": 1024}, {"name": "linear2.weight", "shape": [512, 1024], "q": true, "off": 2872960, "count": 524288, "scale_off": 16464, "nscale": 512}, {"name": "linear2.bias", "shape": [512], "q": false, "f32_off": 16976, "count": 512}, {"name": "linear3.weight", "shape": [256, 512], "q": true, "off": 3397248, "count": 131072, "scale_off": 17488, "nscale": 256}, {"name": "linear3.bias", "shape": [256], "q": false, "f32_off": 17744, "count": 256}, {"name": "linear4.weight", "shape": [1, 256], "q": true, "off": 3528320, "count": 256, "scale_off": 18000, "nscale": 1}, {"name": "linear4.bias", "shape": [1], "q": false, "f32_off": 18001, "count": 1}]}